README.rst
setup.cfg
setup.py
pyxchl/__init__.py
pyxchl/exceptions.py
pyxchl/helpers.py
pyxchl/mixins.py
pyxchl/settings.py
pyxchl/utils.py
pyxchl.egg-info/PKG-INFO
pyxchl.egg-info/SOURCES.txt
pyxchl.egg-info/dependency_links.txt
pyxchl.egg-info/pbr.json
pyxchl.egg-info/requires.txt
pyxchl.egg-info/top_level.txt