Metadata-Version: 1.1
Name: pyxchl
Version: 0.0.10
Summary: XCH library
Home-page: https://bitbucket.org/kas_p/pyxchl
Author: Anton Kulpinov
Author-email: a.kulpinov@gmail.com
License: UNKNOWN
Platform: UNKNOWN
Classifier: Development Status :: 4 - Beta
Classifier: Intended Audience :: Developers
Classifier: Topic :: Software Development :: Build Tools
Classifier: License :: OSI Approved :: MIT License
Classifier: Programming Language :: Python :: 2
Classifier: Programming Language :: Python :: 2.7
